LICENSE
README.md
setup.cfg
setup.py
benchplot/__init__.py
benchplot/plot.py
benchplot.egg-info/PKG-INFO
benchplot.egg-info/SOURCES.txt
benchplot.egg-info/dependency_links.txt
benchplot.egg-info/top_level.txt