Metadata-Version: 2.1
Name: benchplot
Version: 0.0.1
Summary: benchmarking tool for python
Author: Kacper Remzak
Author-email: remzak.k@gmail.com
License: UNKNOWN
Platform: UNKNOWN
Classifier: Development Status :: 1 - Planning
Classifier: Intended Audience :: Developers
Classifier: Programming Language :: Python :: 3
Classifier: Operating System :: Unix
Classifier: Operating System :: MacOS :: MacOS X
Classifier: Operating System :: Microsoft :: Windows
License-File: LICENSE
